zed/__init__.py
zed/cli.py
zed/core/__init__.py
zed/core/commit.py
zed/core/config.py
zed/core/db.py
zed/core/fingerprint.py
zed/core/metrics.py
zed/core/policy.py
zed/core/repo.py
zed/utils/__init__.py
zed/utils/diff.py
zedai-0.1.0.dist-info/licenses/LICENSE
zedai-0.1.0.dist-info/METADATA
zedai-0.1.0.dist-info/WHEEL
zedai-0.1.0.dist-info/entry_points.txt
zedai-0.1.0.dist-info/top_level.txt
zedai-0.1.0.dist-info/RECORD
