Metadata-Version: 2.4
Name: ZedAI
Version: 0.1.0
Summary: A local-first staging VCS for AI agents - quarantine commits before merging to production Git
Author: Shadow VCS Contributors
License: MIT
Requires-Python: >=3.11
License-File: LICENSE
Requires-Dist: click>=8.1.0
Requires-Dist: ruamel.yaml>=0.18.0
Requires-Dist: filelock>=3.13.0
Dynamic: license-file
